aloys/__init__.py
aloys/main.py
aloys/utils.py
aloys-0.1.0.dist-info/METADATA
aloys-0.1.0.dist-info/WHEEL
aloys-0.1.0.dist-info/entry_points.txt
aloys-0.1.0.dist-info/RECORD
